cps_impress/__init__.py
cps_impress/_version.py
cps_impress/sparql.py
cps_impress/urlcache.py
cps_impress/wb.py
cps_impress-1.0.9.dist-info/entry_points.txt
cps_impress-1.0.9.dist-info/licenses/LICENSE
cps_impress-1.0.9.dist-info/WHEEL
cps_impress-1.0.9.dist-info/METADATA
cps_impress-1.0.9.dist-info/RECORD
