Metadata-Version: 2.4
Name: cps_impress
Version: 1.0.9
Summary: CPS Impress
Author: Darron Broad
Requires-Python: >=3.9
Classifier: Programming Language :: Python :: 3
Classifier: Operating System :: OS Independent
License-File: LICENSE
Requires-Dist: WikibaseIntegrator>=0.12
Requires-Dist: lxml
Requires-Dist: jinja2
Requires-Dist: jupyter
Requires-Dist: notebook
Requires-Dist: python-magic
Requires-Dist: cps_wb
Project-URL: Documentation, https://wiki.kewl.org/projects:impress
